chiyi/__init__.py
chiyi/chiyi.py
chiyi/imgconv.py
chiyi-0.0.3.dist-info/LICENSE
chiyi-0.0.3.dist-info/METADATA
chiyi-0.0.3.dist-info/WHEEL
chiyi-0.0.3.dist-info/top_level.txt
chiyi-0.0.3.dist-info/RECORD
