Metadata-Version: 2.1
Name: chiyi
Version: 0.0.3
Summary: Image chiyi.
Home-page: https://github.com/kenblikylee/chiyi
Author: chiyi
Author-email: chishishuan@gmail.com
License: UNKNOWN
Platform: UNKNOWN
Classifier: Programming Language :: Python :: 3
Classifier: License :: OSI Approved :: MIT License
Classifier: Operating System :: OS Independent
Requires-Python: >=3.6
